COPYING
COPYING.LESSER
INSTALL.rst
MANIFEST.in
README.rst
setup.py
staticsfiles_ignoredebug/__init__.py
staticsfiles_ignoredebug.egg-info/PKG-INFO
staticsfiles_ignoredebug.egg-info/SOURCES.txt
staticsfiles_ignoredebug.egg-info/dependency_links.txt
staticsfiles_ignoredebug.egg-info/not-zip-safe
staticsfiles_ignoredebug.egg-info/requires.txt
staticsfiles_ignoredebug.egg-info/top_level.txt
staticsfiles_ignoredebug/views/__init__.py