Metadata-Version: 1.1
Name: staticsfiles-ignoredebug
Version: 0.1.0
Summary: Django Staticsfiles Ignore Debug
Home-page: http://github.com/eoconsulting/django-staticsfiles-ignoredebug
Author: Enterprise Objects Consulting
Author-email: mrsarm@gmail.com
License: AGPL-3
Download-URL: https://github.com/eoconsulting/django-staticsfiles-ignoredebug/tarball/0.1.0
Platform: any
Classifier: Development Status :: 4 - Beta
Classifier: Environment :: Web Environment
Classifier: Intended Audience :: Developers
Classifier: License :: OSI Approved :: GNU Library or Lesser General Public License (LGPL)
Classifier: Operating System :: OS Independent
Classifier: Programming Language :: Python
Classifier: Topic :: Internet :: WWW/HTTP :: Dynamic Content
Classifier: Topic :: Software Development :: Libraries :: Python Modules
